{
  "tasks": [
    {
       "id": 1,
       "title": "Task 1",
       "description": "Description for Task 1",
       "location": "Valletta",
       "date": "1st of Jan",
       "time": "12:00"
    },
    {
       "id": 2,
       "title": "Task 2",
       "description": "Description for Task 2",
       "location": "Sliema",
       "date": "1st of Jan",
       "time": "9:00"
    },
    {
       "id": 3,
       "title": "Task 3",
       "description": "Description for Task 3",
       "location": "Marsaxlokk",
       "date": "1st of Mar",
       "time": "12:00"
    },    
    {
       "id": 4,
       "title": "Task 4",
       "description": "Description for Task 4",
       "location": "Dingli",
       "date": "31st of Mar",
       "time": "12:00"
    },    
    {
       "id": 3,
       "title": "Task 5",
       "description": "Description for Task 5",
       "location": "Rabat",
       "date": "1st of May",
       "time": "21:00"
    }
    
  ]
}
